{
  "_class": "bitmap",
  "clippingMask": "{{0, 0}, {1, 1}}",
  "do_objectID": "3A16C4F7-6AE8-47E9-B512-71D3C6C9326E",
  "exportOptions": {
    "_class": "exportOptions",
    "exportFormats": [
    ],
    "includedLayerIds": [
    ],
    "layerOptions": 0,
    "shouldTrim": false
  },
  "fillReplacesImage": false,
  "frame": {
    "_class": "rect",
    "constrainProportions": true,
    "height": 357,
    "width": 856,
    "x": -148,
    "y": -38
  },
  "image": {
    "_class": "MSJSONFileReference",
    "_ref": "images/8db1326ce9a4421aff836f4fc51aa3815d33c55d",
    "_ref_class": "MSImageData"
  },
  "isFlippedHorizontal": false,
  "isFlippedVertical": false,
  "isLocked": false,
  "isVisible": true,
  "layerListExpandedType": 0,
  "name": "im",
  "nameIsFixed": false,
  "nineSliceCenterRect": "{{0, 0}, {0, 0}}",
  "nineSliceScale": "{0, 0}",
  "resizingConstraint": 63,
  "resizingType": 0,
  "rotation": 0,
  "shouldBreakMaskChain": false,
  "style": {
    "_class": "style",
    "endDecorationType": 0,
    "miterLimit": 10,
    "startDecorationType": 0
  }
}