{
  "_class": "shapeGroup",
  "clippingMaskMode": 0,
  "do_objectID": "34B034B2-E65D-4307-B2BD-D307982A9344",
  "exportOptions": {
    "_class": "exportOptions",
    "exportFormats": [
    ],
    "includedLayerIds": [
    ],
    "layerOptions": 0,
    "shouldTrim": false
  },
  "frame": {
    "_class": "rect",
    "constrainProportions": false,
    "height": 36,
    "width": 130,
    "x": 0,
    "y": 0
  },
  "hasClickThrough": false,
  "hasClippingMask": false,
  "isFlippedHorizontal": false,
  "isFlippedVertical": false,
  "isLocked": false,
  "isVisible": true,
  "layerListExpandedType": 1,
  "layers": [
    {
      "class": "rectangle",
      "id": "A9B412BD-032E-41F8-B047-0BB0A1185250"
    }
  ],
  "name": "Rectangle 8",
  "nameIsFixed": false,
  "resizingConstraint": 63,
  "resizingType": 0,
  "rotation": 0,
  "shouldBreakMaskChain": false,
  "style": {
    "_class": "style",
    "borders": [
      {
        "_class": "border",
        "color": {
          "_class": "color",
          "alpha": 1,
          "blue": 0.7568627450980392,
          "green": 0.7568627450980392,
          "red": 0.7568627450980392
        },
        "fillType": 0,
        "isEnabled": true,
        "position": 1,
        "thickness": 1
      }
    ],
    "endDecorationType": 0,
    "fills": [
      {
        "_class": "fill",
        "color": {
          "_class": "color",
          "alpha": 1,
          "blue": 0.4,
          "green": 0.4,
          "red": 0.4
        },
        "fillType": 0,
        "isEnabled": true,
        "noiseIndex": 0,
        "noiseIntensity": 0,
        "patternFillType": 1,
        "patternTileScale": 1
      }
    ],
    "miterLimit": 10,
    "startDecorationType": 0
  },
  "windingRule": 1
}