{
  "_class": "shapeGroup",
  "clippingMaskMode": 0,
  "do_objectID": "FB731D44-CEA5-439B-84C9-3925ACC92AA9",
  "exportOptions": {
    "_class": "exportOptions",
    "exportFormats": [
    ],
    "includedLayerIds": [
    ],
    "layerOptions": 0,
    "shouldTrim": false
  },
  "frame": {
    "_class": "rect",
    "constrainProportions": false,
    "height": 86.00003000000004,
    "width": 58.16999600000001,
    "x": 69,
    "y": 0
  },
  "hasClickThrough": false,
  "hasClippingMask": false,
  "isFlippedHorizontal": true,
  "isFlippedVertical": false,
  "isLocked": false,
  "isVisible": true,
  "layerListExpandedType": 1,
  "layers": [
    {
      "class": "shapePath",
      "id": "29882D74-77B9-46C8-BB3C-C212B035FF64"
    },
    {
      "class": "shapePath",
      "id": "444287F5-D590-498C-9028-282886129AC7"
    },
    {
      "class": "shapePath",
      "id": "9833FCA4-94F2-4BF2-90E6-F51C80D61D5A"
    }
  ],
  "name": "Shape Copy",
  "nameIsFixed": false,
  "resizingConstraint": 63,
  "resizingType": 0,
  "rotation": 0,
  "shouldBreakMaskChain": false,
  "style": {
    "_class": "style",
    "endDecorationType": 0,
    "fills": [
      {
        "_class": "fill",
        "color": {
          "_class": "color",
          "alpha": 1,
          "blue": 0,
          "green": 0,
          "red": 0
        },
        "fillType": 0,
        "isEnabled": true,
        "noiseIndex": 0,
        "noiseIntensity": 0,
        "patternFillType": 1,
        "patternTileScale": 1
      }
    ],
    "miterLimit": 10,
    "startDecorationType": 0
  },
  "windingRule": 1
}